LICENSE
README.md
setup.py
cerebro/__init__.py
cerebro/datastructs/__init__.py
cerebro/datastructs/stack.py
cerebro/datastructs/trees/__init__.py
cerebro/datastructs/trees/general.py
cerebro/designs/__init__.py
cerebro/designs/behaviours/__init__.py
cerebro/designs/behaviours/batchprocess.py
cerebro/designs/behaviours/component.py
cerebro/designs/creations/__init__.py
cerebro/designs/creations/singleton.py
cerebro/io/__init__.py
cerebro/io/path.py
cerebro/logs/__init__.py
cerebro/logs/logging.py
cerebro/logs/records/__init__.py
cerebro/logs/records/visual.py
cerebro/objects/__init__.py
cerebro/objects/meta.py
cerebro/serializations/__init__.py
cerebro/serializations/base.py
cerebro/serializations/json.py
cerebro_toolkit.egg-info/PKG-INFO
cerebro_toolkit.egg-info/SOURCES.txt
cerebro_toolkit.egg-info/dependency_links.txt
cerebro_toolkit.egg-info/namespace_packages.txt
cerebro_toolkit.egg-info/top_level.txt
cerebro_toolkit.egg-info/zip-safe